{
    "CNNGRU-BNB-ITER0": {
        "per_class": {
            "train": {
                "precision": [
                    0.9806167400881057,
                    0.9733434881949733,
                    0.9744599047967777
                ],
                "recall": [
                    0.9471444780635401,
                    0.990505715946522,
                    0.9906933457422057
                ],
                "f1_score": [
                    0.9635900149102976,
                    0.9818496110630941,
                    0.9825095758918271
                ],
                "support": [
                    10576,
                    10322,
                    10745
                ]
            },
            "val": {
                "precision": [
                    0.9704235942852368,
                    0.14573643410852713,
                    0.12589928057553956
                ],
                "recall": [
                    0.9180366740436294,
                    0.36293436293436293,
                    0.2702702702702703
                ],
                "f1_score": [
                    0.9435035132610372,
                    0.2079646017699115,
                    0.17177914110429449
                ],
                "support": [
                    12652,
                    259,
                    259
                ]
            },
            "test": {
                "precision": [
                    0.969663642195949,
                    0.18473895582329317,
                    0.1300639658848614
                ],
                "recall": [
                    0.9285588906441987,
                    0.38016528925619836,
                    0.25206611570247933
                ],
                "f1_score": [
                    0.9486662183366958,
                    0.24864864864864863,
                    0.17158931082981715
                ],
                "support": [
                    11394,
                    242,
                    242
                ]
            }
        },
        "avg_macro": {
            "train": {
                "precision": 0.9761400443599522,
                "recall": 0.9761145132507559,
                "f1_score": 0.9759830672884062
            },
            "val": {
                "precision": 0.41401976965643456,
                "recall": 0.5170804357494209,
                "f1_score": 0.4410824187117477
            },
            "test": {
                "precision": 0.4281555213013679,
                "recall": 0.5202634318676255,
                "f1_score": 0.45630139260505387
            }
        },
        "annualised_returns": 0.8970968487601438
    },
    "CNNGRU-BNB-ITER1": {
        "per_class": {
            "train": {
                "precision": [
                    0.9802304788396583,
                    0.969303974622131,
                    0.9701341665135086
                ],
                "recall": [
                    0.9378386084972912,
                    0.9898056402439024,
                    0.9913606911447084
                ],
                "f1_score": [
                    0.9585660853936951,
                    0.9794475346469312,
                    0.980632576285356
                ],
                "support": [
                    10521,
                    10496,
                    10649
                ]
            },
            "val": {
                "precision": [
                    0.9735440791141915,
                    0.1800302571860817,
                    0.12831858407079647
                ],
                "recall": [
                    0.9104418623033752,
                    0.4576923076923077,
                    0.3359073359073359
                ],
                "f1_score": [
                    0.9409361980230373,
                    0.25841476655808904,
                    0.1856990394877268
                ],
                "support": [
                    12651,
                    260,
                    259
                ]
            },
            "test": {
                "precision": [
                    0.9703244892299159,
                    0.1782608695652174,
                    0.1384083044982699
                ],
                "recall": [
                    0.9229686950404502,
                    0.34024896265560167,
                    0.3305785123966942
                ],
                "f1_score": [
                    0.9460543512551265,
                    0.23395149786019973,
                    0.1951219512195122
                ],
                "support": [
                    11372,
                    241,
                    242
                ]
            }
        },
        "avg_macro": {
            "train": {
                "precision": 0.9732228733250993,
                "recall": 0.9730016466286339,
                "f1_score": 0.9728820654419942
            },
            "val": {
                "precision": 0.4272976401236899,
                "recall": 0.5680138353010062,
                "f1_score": 0.4616833346896178
            },
            "test": {
                "precision": 0.42899788776446773,
                "recall": 0.5312653900309153,
                "f1_score": 0.45837593344494615
            }
        },
        "annualised_returns": 0.545333398274906
    },
    "CNNGRU-BNB-ITER2": {
        "per_class": {
            "train": {
                "precision": [
                    0.9694225338397118,
                    0.9617215946223509,
                    0.9623681015967878
                ],
                "recall": [
                    0.924498514115899,
                    0.9838586437440305,
                    0.986125729595254
                ],
                "f1_score": [
                    0.9464277225840186,
                    0.9726641801614654,
                    0.9741020793950851
                ],
                "support": [
                    10768,
                    10470,
                    10451
                ]
            },
            "val": {
                "precision": [
                    0.9730143866519111,
                    0.1539491298527443,
                    0.1301775147928994
                ],
                "recall": [
                    0.9035573122529644,
                    0.4423076923076923,
                    0.3384615384615385
                ],
                "f1_score": [
                    0.9370004508751076,
                    0.22840119165839126,
                    0.18803418803418803
                ],
                "support": [
                    12650,
                    260,
                    260
                ]
            },
            "test": {
                "precision": [
                    0.9710199473089951,
                    0.17328519855595667,
                    0.11846153846153847
                ],
                "recall": [
                    0.9091709981499427,
                    0.4,
                    0.31950207468879666
                ],
                "f1_score": [
                    0.9390782110196096,
                    0.24181360201511334,
                    0.17283950617283952
                ],
                "support": [
                    11351,
                    240,
                    241
                ]
            }
        },
        "avg_macro": {
            "train": {
                "precision": 0.9645040766862835,
                "recall": 0.9648276291517278,
                "f1_score": 0.9643979940468563
            },
            "val": {
                "precision": 0.4190470104325183,
                "recall": 0.5614421810073984,
                "f1_score": 0.45114527685589567
            },
            "test": {
                "precision": 0.42092222810883007,
                "recall": 0.5428910242795798,
                "f1_score": 0.45124377306918756
            }
        },
        "annualised_returns": 0.43334885105140786
    },
    "CNNGRU-BNB-ITER3": {
        "per_class": {
            "train": {
                "precision": [
                    0.8663649100118547,
                    0.8852328159645233,
                    0.8807133894963255
                ],
                "recall": [
                    0.7538447111777945,
                    0.9456181904310753,
                    0.9365291146478605
                ],
                "f1_score": [
                    0.8061976633405206,
                    0.9144296839212093,
                    0.9077640755623297
                ],
                "support": [
                    10664,
                    10555,
                    10493
                ]
            },
            "val": {
                "precision": [
                    0.98046875,
                    0.1433659839715049,
                    0.11505791505791506
                ],
                "recall": [
                    0.8333596837944665,
                    0.6192307692307693,
                    0.573076923076923
                ],
                "f1_score": [
                    0.9009486368686437,
                    0.23282718727404195,
                    0.19163987138263663
                ],
                "support": [
                    12650,
                    260,
                    260
                ]
            },
            "test": {
                "precision": [
                    0.9788725241239208,
                    0.16488730723606168,
                    0.11953612845673506
                ],
                "recall": [
                    0.8507238700564972,
                    0.5791666666666667,
                    0.5560165975103735
                ],
                "f1_score": [
                    0.9103103008548622,
                    0.2566943674976916,
                    0.19676945668135096
                ],
                "support": [
                    11328,
                    240,
                    241
                ]
            }
        },
        "avg_macro": {
            "train": {
                "precision": 0.8774370384909012,
                "recall": 0.87866400541891,
                "f1_score": 0.8761304742746866
            },
            "val": {
                "precision": 0.41296421634313996,
                "recall": 0.6752224587007195,
                "f1_score": 0.44180523184177406
            },
            "test": {
                "precision": 0.42109865327223917,
                "recall": 0.6619690447445125,
                "f1_score": 0.45459137501130154
            }
        },
        "annualised_returns": 0.426270409039085
    },
    "CNNGRU-BNB-ITER4": {
        "per_class": {
            "train": {
                "precision": [
                    0.9573200992555831,
                    0.9512285239238869,
                    0.9551412220786413
                ],
                "recall": [
                    0.9048691246833662,
                    0.9792696842906048,
                    0.9799242424242425
                ],
                "f1_score": [
                    0.9303559371081316,
                    0.9650454502858214,
                    0.9673740301018978
                ],
                "support": [
                    10659,
                    10516,
                    10560
                ]
            },
            "val": {
                "precision": [
                    0.9728265470244646,
                    0.15789473684210525,
                    0.1375166889185581
                ],
                "recall": [
                    0.9084584980237154,
                    0.36923076923076925,
                    0.39615384615384613
                ],
                "f1_score": [
                    0.9395413481584434,
                    0.2211981566820276,
                    0.2041625371655104
                ],
                "support": [
                    12650,
                    260,
                    260
                ]
            },
            "test": {
                "precision": [
                    0.9706377407892276,
                    0.18025751072961374,
                    0.13099041533546327
                ],
                "recall": [
                    0.9180965858836017,
                    0.35,
                    0.3416666666666667
                ],
                "f1_score": [
                    0.9436363636363637,
                    0.23796033994334279,
                    0.18937644341801385
                ],
                "support": [
                    11306,
                    240,
                    240
                ]
            }
        },
        "avg_macro": {
            "train": {
                "precision": 0.9545632817527038,
                "recall": 0.9546876837994045,
                "f1_score": 0.954258472498617
            },
            "val": {
                "precision": 0.422745990928376,
                "recall": 0.5579477044694435,
                "f1_score": 0.4549673473353271
            },
            "test": {
                "precision": 0.4272952222847682,
                "recall": 0.5365877508500895,
                "f1_score": 0.45699104899924015
            }
        },
        "annualised_returns": 0.01170695124051968
    },
    "CNNGRU-BNB-ITER5": {
        "per_class": {
            "train": {
                "precision": [
                    0.9666232334369049,
                    0.9630681818181818,
                    0.9631060815162389
                ],
                "recall": [
                    0.9230474732006125,
                    0.9847263868065967,
                    0.9840195525474713
                ],
                "f1_score": [
                    0.9443329253365973,
                    0.9737768717568569,
                    0.9734505044869112
                ],
                "support": [
                    10448,
                    10672,
                    10638
                ]
            },
            "val": {
                "precision": [
                    0.968591526255521,
                    0.1551155115511551,
                    0.1242603550295858
                ],
                "recall": [
                    0.9361264822134387,
                    0.36153846153846153,
                    0.16153846153846155
                ],
                "f1_score": [
                    0.9520823283486092,
                    0.21709006928406463,
                    0.14046822742474915
                ],
                "support": [
                    12650,
                    260,
                    260
                ]
            },
            "test": {
                "precision": [
                    0.9674870583961493,
                    0.14096916299559473,
                    0.1912751677852349
                ],
                "recall": [
                    0.9440801134349521,
                    0.26778242677824265,
                    0.2375
                ],
                "f1_score": [
                    0.9556402780892577,
                    0.18470418470418468,
                    0.21189591078066913
                ],
                "support": [
                    11284,
                    239,
                    240
                ]
            }
        },
        "avg_macro": {
            "train": {
                "precision": 0.9642658322571086,
                "recall": 0.9639311375182268,
                "f1_score": 0.9638534338601218
            },
            "val": {
                "precision": 0.4159891309454206,
                "recall": 0.48640113509678734,
                "f1_score": 0.43654687501914097
            },
            "test": {
                "precision": 0.43324379639232635,
                "recall": 0.48312084673773165,
                "f1_score": 0.45074679119137046
            }
        },
        "annualised_returns": 0.527758155651852
    },
    "CNNGRU-BNB-ITER6": {
        "per_class": {
            "train": {
                "precision": [
                    0.8955836302775079,
                    0.9006008128644637,
                    0.9038564542046064
                ],
                "recall": [
                    0.7902057926829268,
                    0.9546689144890887,
                    0.9544683257918553
                ],
                "f1_score": [
                    0.8396011540213595,
                    0.9268470106842466,
                    0.9284731774415406
                ],
                "support": [
                    10496,
                    10677,
                    10608
                ]
            },
            "val": {
                "precision": [
                    0.9759079793496965,
                    0.15505913272010513,
                    0.09868421052631579
                ],
                "recall": [
                    0.8517113271678128,
                    0.45384615384615384,
                    0.5212355212355212
                ],
                "f1_score": [
                    0.9095897349316224,
                    0.23114593535749264,
                    0.16594960049170251
                ],
                "support": [
                    12651,
                    260,
                    259
                ]
            },
            "test": {
                "precision": [
                    0.973760063611967,
                    0.17058823529411765,
                    0.10949529512403763
                ],
                "recall": [
                    0.8699937838557854,
                    0.36401673640167365,
                    0.5333333333333333
                ],
                "f1_score": [
                    0.9189569458774974,
                    0.23230974632843795,
                    0.18168914123491836
                ],
                "support": [
                    11261,
                    239,
                    240
                ]
            }
        },
        "avg_macro": {
            "train": {
                "precision": 0.9000136324488593,
                "recall": 0.8997810109879568,
                "f1_score": 0.8983071140490488
            },
            "val": {
                "precision": 0.4098837741987058,
                "recall": 0.6089310007498293,
                "f1_score": 0.4355617569269392
            },
            "test": {
                "precision": 0.4179478646767074,
                "recall": 0.5891146178635974,
                "f1_score": 0.44431861114695126
            }
        },
        "annualised_returns": 0.059860463639496375
    },
    "CNNGRU-BNB-ITER7": {
        "per_class": {
            "train": {
                "precision": [
                    0.9428917364544446,
                    0.9414528370075894,
                    0.9409699769053118
                ],
                "recall": [
                    0.8789503386004515,
                    0.9742870500233755,
                    0.9722248735324998
                ],
                "f1_score": [
                    0.9097989582826267,
                    0.9575885677526076,
                    0.9563421274997652
                ],
                "support": [
                    10632,
                    10695,
                    10477
                ]
            },
            "val": {
                "precision": [
                    0.9726542471372415,
                    0.15063291139240506,
                    0.11946902654867257
                ],
                "recall": [
                    0.8997628458498024,
                    0.4576923076923077,
                    0.31153846153846154
                ],
                "f1_score": [
                    0.9347897503285151,
                    0.22666666666666666,
                    0.1727078891257996
                ],
                "support": [
                    12650,
                    260,
                    260
                ]
            },
            "test": {
                "precision": [
                    0.9700275064023522,
                    0.17345132743362832,
                    0.10509031198686371
                ],
                "recall": [
                    0.9099564018151081,
                    0.4100418410041841,
                    0.26778242677824265
                ],
                "f1_score": [
                    0.9390322284455054,
                    0.24378109452736318,
                    0.1509433962264151
                ],
                "support": [
                    11239,
                    239,
                    239
                ]
            }
        },
        "avg_macro": {
            "train": {
                "precision": 0.9417715167891152,
                "recall": 0.941820754052109,
                "f1_score": 0.9412432178449999
            },
            "val": {
                "precision": 0.414252061692773,
                "recall": 0.5563312050268572,
                "f1_score": 0.44472143537366043
            },
            "test": {
                "precision": 0.41618971527428145,
                "recall": 0.5292602231991783,
                "f1_score": 0.4445855730664279
            }
        },
        "annualised_returns": 0.3775446157923674
    },
    "CNNGRU-BNB-ITER8": {
        "per_class": {
            "train": {
                "precision": [
                    0.9815938907382025,
                    0.9743209418744785,
                    0.9749676704230557
                ],
                "recall": [
                    0.9481747682996028,
                    0.9903882397286091,
                    0.9919180528145851
                ],
                "f1_score": [
                    0.9645949586299788,
                    0.9822888920042991,
                    0.9833698234499465
                ],
                "support": [
                    10574,
                    10612,
                    10641
                ]
            },
            "val": {
                "precision": [
                    0.9720016715419975,
                    0.15625,
                    0.1497005988023952
                ],
                "recall": [
                    0.9193675889328063,
                    0.4230769230769231,
                    0.28846153846153844
                ],
                "f1_score": [
                    0.9449522648791387,
                    0.22821576763485477,
                    0.1971090670170828
                ],
                "support": [
                    12650,
                    260,
                    260
                ]
            },
            "test": {
                "precision": [
                    0.9705744978981784,
                    0.16129032258064516,
                    0.16937354988399073
                ],
                "recall": [
                    0.926355206847361,
                    0.37656903765690375,
                    0.3054393305439331
                ],
                "f1_score": [
                    0.9479494548606359,
                    0.2258469259723965,
                    0.21791044776119406
                ],
                "support": [
                    11216,
                    239,
                    239
                ]
            }
        },
        "avg_macro": {
            "train": {
                "precision": 0.9769608343452455,
                "recall": 0.9768270202809323,
                "f1_score": 0.9767512246947415
            },
            "val": {
                "precision": 0.42598409011479754,
                "recall": 0.5436353501570893,
                "f1_score": 0.45675903317702543
            },
            "test": {
                "precision": 0.43374612345427144,
                "recall": 0.5361211916827326,
                "f1_score": 0.4639022761980754
            }
        },
        "annualised_returns": 0.5804133963271658
    },
    "CNNGRU-BNB-ITER9": {
        "per_class": {
            "train": {
                "precision": [
                    0.9496811478676763,
                    0.950950950950951,
                    0.9523325635103926
                ],
                "recall": [
                    0.9003400717929341,
                    0.9772748527073787,
                    0.9752152114274903
                ],
                "f1_score": [
                    0.9243526331102705,
                    0.9639332164929435,
                    0.9636380631893813
                ],
                "support": [
                    10586,
                    10693,
                    10571
                ]
            },
            "val": {
                "precision": [
                    0.9738735651875964,
                    0.14847161572052403,
                    0.13448275862068965
                ],
                "recall": [
                    0.8986641372223539,
                    0.5230769230769231,
                    0.30115830115830117
                ],
                "f1_score": [
                    0.9347584789311408,
                    0.23129251700680276,
                    0.18593563766388557
                ],
                "support": [
                    12651,
                    260,
                    259
                ]
            },
            "test": {
                "precision": [
                    0.9705488621151271,
                    0.1495601173020528,
                    0.12617702448210924
                ],
                "recall": [
                    0.9067357512953368,
                    0.42857142857142855,
                    0.2803347280334728
                ],
                "f1_score": [
                    0.9375577313874007,
                    0.2217391304347826,
                    0.17402597402597403
                ],
                "support": [
                    11194,
                    238,
                    239
                ]
            }
        },
        "avg_macro": {
            "train": {
                "precision": 0.95098822077634,
                "recall": 0.950943378642601,
                "f1_score": 0.9506413042641985
            },
            "val": {
                "precision": 0.41894264650960333,
                "recall": 0.574299787152526,
                "f1_score": 0.45066221120060973
            },
            "test": {
                "precision": 0.4154286679664297,
                "recall": 0.5385473026334128,
                "f1_score": 0.4444409452827191
            }
        },
        "annualised_returns": 0.2994251115483302
    },
    "CNNGRU-BNB-ITER10": {
        "per_class": {
            "train": {
                "precision": [
                    0.965052934525645,
                    0.9460913983398704,
                    0.946069224577408
                ],
                "recall": [
                    0.8871775488991779,
                    0.9846212265046516,
                    0.9834510970621049
                ],
                "f1_score": [
                    0.9244781410003938,
                    0.9649718565381216,
                    0.9643980489583808
                ],
                "support": [
                    10583,
                    10534,
                    10756
                ]
            },
            "val": {
                "precision": [
                    0.9794941282746161,
                    0.14337240757439135,
                    0.13218970736629668
                ],
                "recall": [
                    0.8569509207302616,
                    0.6138996138996139,
                    0.5077519379844961
                ],
                "f1_score": [
                    0.9141339628208911,
                    0.23245614035087722,
                    0.20976781425140115
                ],
                "support": [
                    12653,
                    259,
                    258
                ]
            },
            "test": {
                "precision": [
                    0.9764041544822023,
                    0.15547703180212014,
                    0.12585034013605442
                ],
                "recall": [
                    0.8667979590009847,
                    0.5546218487394958,
                    0.46443514644351463
                ],
                "f1_score": [
                    0.9183421851289832,
                    0.24287028518859244,
                    0.19803746654772525
                ],
                "support": [
                    11171,
                    238,
                    239
                ]
            }
        },
        "avg_macro": {
            "train": {
                "precision": 0.9524045191476412,
                "recall": 0.9517499574886448,
                "f1_score": 0.951282682165632
            },
            "val": {
                "precision": 0.4183520810717681,
                "recall": 0.6595341575381238,
                "f1_score": 0.45211930580772314
            },
            "test": {
                "precision": 0.41924384214012567,
                "recall": 0.6286183180613317,
                "f1_score": 0.4530833122884337
            }
        },
        "annualised_returns": -0.015083891228229174
    },
    "CNNGRU-BNB-ITER11": {
        "per_class": {
            "train": {
                "precision": [
                    0.970807210031348,
                    0.9702053538687202,
                    0.9672541743970315
                ],
                "recall": [
                    0.9360536507036932,
                    0.9864839671886652,
                    0.9854456100557604
                ],
                "f1_score": [
                    0.9531137292618418,
                    0.9782769458310222,
                    0.9762651561256496
                ],
                "support": [
                    10587,
                    10728,
                    10581
                ]
            },
            "val": {
                "precision": [
                    0.9713121569931814,
                    0.171900826446281,
                    0.1261595547309833
                ],
                "recall": [
                    0.9231802734529361,
                    0.4015444015444015,
                    0.26356589147286824
                ],
                "f1_score": [
                    0.9466347907127517,
                    0.24074074074074076,
                    0.17063989962358847
                ],
                "support": [
                    12653,
                    259,
                    258
                ]
            },
            "test": {
                "precision": [
                    0.9700300638857572,
                    0.1746641074856046,
                    0.14565217391304347
                ],
                "recall": [
                    0.9261750986724077,
                    0.38235294117647056,
                    0.2803347280334728
                ],
                "f1_score": [
                    0.9475954478707782,
                    0.23978919631093543,
                    0.1917024320457797
                ],
                "support": [
                    11148,
                    238,
                    239
                ]
            }
        },
        "avg_macro": {
            "train": {
                "precision": 0.9694222460990333,
                "recall": 0.9693277426493729,
                "f1_score": 0.9692186104061712
            },
            "val": {
                "precision": 0.42312417939014857,
                "recall": 0.529430188823402,
                "f1_score": 0.452671810359027
            },
            "test": {
                "precision": 0.4301154484281351,
                "recall": 0.5296209226274504,
                "f1_score": 0.45969569207583105
            }
        },
        "annualised_returns": 0.11320766661130244
    },
    "CNNGRU-BNB-ITER12": {
        "per_class": {
            "train": {
                "precision": [
                    0.9680775114737379,
                    0.9537376328325394,
                    0.9544561528844436
                ],
                "recall": [
                    0.9033977348434377,
                    0.984957426679281,
                    0.985795978601734
                ],
                "f1_score": [
                    0.9346199291059472,
                    0.9690961556362282,
                    0.9698729582577132
                ],
                "support": [
                    10507,
                    10570,
                    10842
                ]
            },
            "val": {
                "precision": [
                    0.9774362618814959,
                    0.1514543630892678,
                    0.12445414847161572
                ],
                "recall": [
                    0.8697336178958185,
                    0.5807692307692308,
                    0.44015444015444016
                ],
                "f1_score": [
                    0.9204450393173833,
                    0.24025457438345263,
                    0.19404255319148936
                ],
                "support": [
                    12651,
                    260,
                    259
                ]
            },
            "test": {
                "precision": [
                    0.9761644651901877,
                    0.17079889807162535,
                    0.137546468401487
                ],
                "recall": [
                    0.8833468140559001,
                    0.5232067510548524,
                    0.46638655462184875
                ],
                "f1_score": [
                    0.9274391394602755,
                    0.25752855659397716,
                    0.2124401913875598
                ],
                "support": [
                    11127,
                    237,
                    238
                ]
            }
        },
        "avg_macro": {
            "train": {
                "precision": 0.9587570990635736,
                "recall": 0.9580503800414841,
                "f1_score": 0.9578630143332961
            },
            "val": {
                "precision": 0.41778159114745983,
                "recall": 0.6302190962731632,
                "f1_score": 0.45158072229744173
            },
            "test": {
                "precision": 0.42816994388776664,
                "recall": 0.6243133732442004,
                "f1_score": 0.4658026291472708
            }
        },
        "annualised_returns": 0.010496014794450836
    },
    "CNNGRU-BNB-ITER13": {
        "per_class": {
            "train": {
                "precision": [
                    0.9273772204806687,
                    0.9229736983360172,
                    0.922726460603895
                ],
                "recall": [
                    0.8371851712102631,
                    0.9658303688447856,
                    0.9690402476780186
                ],
                "f1_score": [
                    0.8799762034604135,
                    0.9439158279963403,
                    0.9453164325264265
                ],
                "support": [
                    10601,
                    10682,
                    10659
                ]
            },
            "val": {
                "precision": [
                    0.9758100114770019,
                    0.13027387120651368,
                    0.1443089430894309
                ],
                "recall": [
                    0.8738240177089098,
                    0.6743295019157088,
                    0.27307692307692305
                ],
                "f1_score": [
                    0.9220053386720053,
                    0.2183622828784119,
                    0.18882978723404256
                ],
                "support": [
                    12649,
                    261,
                    260
                ]
            },
            "test": {
                "precision": [
                    0.973007839634812,
                    0.13619402985074627,
                    0.12790697674418605
                ],
                "recall": [
                    0.8828561138123537,
                    0.6186440677966102,
                    0.2320675105485232
                ],
                "f1_score": [
                    0.9257423405561063,
                    0.2232415902140673,
                    0.1649175412293853
                ],
                "support": [
                    11106,
                    236,
                    237
                ]
            }
        },
        "avg_macro": {
            "train": {
                "precision": 0.924359126473527,
                "recall": 0.9240185959110224,
                "f1_score": 0.9230694879943936
            },
            "val": {
                "precision": 0.41679760859098214,
                "recall": 0.6070768142338472,
                "f1_score": 0.4430658029281533
            },
            "test": {
                "precision": 0.4123696154099148,
                "recall": 0.5778558973858291,
                "f1_score": 0.4379671573331863
            }
        },
        "annualised_returns": -0.04153117928656558
    },
    "CNNGRU-BNB-ITER14": {
        "per_class": {
            "train": {
                "precision": [
                    0.9793218345746766,
                    0.973816717019134,
                    0.9741649750876545
                ],
                "recall": [
                    0.9463964390567289,
                    0.9899488134015821,
                    0.9903386173904887
                ],
                "f1_score": [
                    0.9625776621875453,
                    0.9818165035997785,
                    0.9821852179171126
                ],
                "support": [
                    10559,
                    10745,
                    10661
                ]
            },
            "val": {
                "precision": [
                    0.9694467382328654,
                    0.15156794425087108,
                    0.12962962962962962
                ],
                "recall": [
                    0.9280632411067193,
                    0.3346153846153846,
                    0.2423076923076923
                ],
                "f1_score": [
                    0.9483037156704361,
                    0.20863309352517984,
                    0.16890080428954424
                ],
                "support": [
                    12650,
                    260,
                    260
                ]
            },
            "test": {
                "precision": [
                    0.9691271400505193,
                    0.17703349282296652,
                    0.1514476614699332
                ],
                "recall": [
                    0.9345904005774088,
                    0.3135593220338983,
                    0.288135593220339
                ],
                "f1_score": [
                    0.9515454921232719,
                    0.22629969418960247,
                    0.19854014598540146
                ],
                "support": [
                    11084,
                    236,
                    236
                ]
            }
        },
        "avg_macro": {
            "train": {
                "precision": 0.9757678422271551,
                "recall": 0.9755612899495999,
                "f1_score": 0.9755264612348121
            },
            "val": {
                "precision": 0.41688143737112204,
                "recall": 0.5016621060099321,
                "f1_score": 0.4419458711617201
            },
            "test": {
                "precision": 0.43253609811447297,
                "recall": 0.5120951052772154,
                "f1_score": 0.4587951107660919
            }
        },
        "annualised_returns": 0.3264787932723532
    },
    "CNNGRU-BNB-ITER15": {
        "per_class": {
            "train": {
                "precision": [
                    0.9672276350752879,
                    0.9658451029262439,
                    0.9701655448426414
                ],
                "recall": [
                    0.9336880106403193,
                    0.9832722488487924,
                    0.9856760003696516
                ],
                "f1_score": [
                    0.9501619374486392,
                    0.9744807674396945,
                    0.9778592711437085
                ],
                "support": [
                    10526,
                    10641,
                    10821
                ]
            },
            "val": {
                "precision": [
                    0.9701248877642641,
                    0.16819012797074953,
                    0.16129032258064516
                ],
                "recall": [
                    0.9394514267646826,
                    0.35384615384615387,
                    0.23166023166023167
                ],
                "f1_score": [
                    0.9545418038711748,
                    0.2280049566294919,
                    0.19017432646592708
                ],
                "support": [
                    12651,
                    260,
                    259
                ]
            },
            "test": {
                "precision": [
                    0.9688076781100037,
                    0.1876675603217158,
                    0.19135802469135801
                ],
                "recall": [
                    0.9490146447297053,
                    0.2978723404255319,
                    0.2627118644067797
                ],
                "f1_score": [
                    0.9588090236551283,
                    0.2302631578947368,
                    0.22142857142857142
                ],
                "support": [
                    11062,
                    235,
                    236
                ]
            }
        },
        "avg_macro": {
            "train": {
                "precision": 0.967746094281391,
                "recall": 0.9675454199529211,
                "f1_score": 0.9675006586773475
            },
            "val": {
                "precision": 0.433201779438553,
                "recall": 0.5083192707570227,
                "f1_score": 0.45757369565553124
            },
            "test": {
                "precision": 0.44927775437435913,
                "recall": 0.5031996165206724,
                "f1_score": 0.47016691765947877
            }
        },
        "annualised_returns": 0.6327368493274723
    },
    "CNNGRU-BNB-ITER16": {
        "per_class": {
            "train": {
                "precision": [
                    0.9582644628099174,
                    0.9333393226125236,
                    0.9388392857142858
                ],
                "recall": [
                    0.8666728954498739,
                    0.9812978180787758,
                    0.9807853744986476
                ],
                "f1_score": [
                    0.9101702399058039,
                    0.9567179298277927,
                    0.9593540440673327
                ],
                "support": [
                    10703,
                    10587,
                    10721
                ]
            },
            "val": {
                "precision": [
                    0.9800181653042689,
                    0.1492822966507177,
                    0.13004484304932734
                ],
                "recall": [
                    0.8530318602261048,
                    0.5977011494252874,
                    0.5576923076923077
                ],
                "f1_score": [
                    0.9121264635022612,
                    0.23889739663093418,
                    0.21090909090909093
                ],
                "support": [
                    12649,
                    261,
                    260
                ]
            },
            "test": {
                "precision": [
                    0.9754688291941206,
                    0.16052631578947368,
                    0.11864406779661017
                ],
                "recall": [
                    0.8715696042025178,
                    0.5213675213675214,
                    0.44680851063829785
                ],
                "f1_score": [
                    0.9205969578111546,
                    0.24547283702213277,
                    0.1875
                ],
                "support": [
                    11041,
                    234,
                    235
                ]
            }
        },
        "avg_macro": {
            "train": {
                "precision": 0.9434810237122422,
                "recall": 0.942918696009099,
                "f1_score": 0.9420807379336432
            },
            "val": {
                "precision": 0.4197817683347713,
                "recall": 0.6694751057812333,
                "f1_score": 0.4539776503474288
            },
            "test": {
                "precision": 0.4182130709267348,
                "recall": 0.613248545402779,
                "f1_score": 0.45118993161109583
            }
        },
        "annualised_returns": -0.10882939336344344
    },
    "CNNGRU-BNB-ITER17": {
        "per_class": {
            "train": {
                "precision": [
                    0.979042791695097,
                    0.9686052972772735,
                    0.971303634872916
                ],
                "recall": [
                    0.9388670779584969,
                    0.9890307328605201,
                    0.9908001115137999
                ],
                "f1_score": [
                    0.9585341413370234,
                    0.9787114583820709,
                    0.9809550096605023
                ],
                "support": [
                    10698,
                    10575,
                    10761
                ]
            },
            "val": {
                "precision": [
                    0.9699097291875627,
                    0.14896988906497624,
                    0.11478260869565217
                ],
                "recall": [
                    0.9173122529644269,
                    0.36153846153846153,
                    0.25384615384615383
                ],
                "f1_score": [
                    0.9428780368895749,
                    0.21099887766554434,
                    0.15808383233532936
                ],
                "support": [
                    12650,
                    260,
                    260
                ]
            },
            "test": {
                "precision": [
                    0.9688541765882465,
                    0.17796610169491525,
                    0.1124031007751938
                ],
                "recall": [
                    0.9232165547286258,
                    0.358974358974359,
                    0.24680851063829787
                ],
                "f1_score": [
                    0.9454849653762142,
                    0.23796033994334279,
                    0.1544607190412783
                ],
                "support": [
                    11018,
                    234,
                    235
                ]
            }
        },
        "avg_macro": {
            "train": {
                "precision": 0.9729839079484289,
                "recall": 0.9728993074442723,
                "f1_score": 0.9727335364598656
            },
            "val": {
                "precision": 0.4112207423160637,
                "recall": 0.5108989561163474,
                "f1_score": 0.43732024896348287
            },
            "test": {
                "precision": 0.4197411263527852,
                "recall": 0.5096664747804275,
                "f1_score": 0.44596867478694513
            }
        },
        "annualised_returns": 0.32966065891227747
    },
    "CNNGRU-BNB-ITER18": {
        "per_class": {
            "train": {
                "precision": [
                    0.9776170462320399,
                    0.9687071095251166,
                    0.9698082040928696
                ],
                "recall": [
                    0.9371310784221868,
                    0.9881463505693485,
                    0.9904404873477038
                ],
                "f1_score": [
                    0.9569460390355913,
                    0.978330176038442,
                    0.9800157648258915
                ],
                "support": [
                    10673,
                    10714,
                    10670
                ]
            },
            "val": {
                "precision": [
                    0.9726582278481013,
                    0.16374269005847952,
                    0.13364779874213836
                ],
                "recall": [
                    0.911218278124753,
                    0.42911877394636017,
                    0.3269230769230769
                ],
                "f1_score": [
                    0.9409363647495818,
                    0.23703703703703702,
                    0.18973214285714288
                ],
                "support": [
                    12649,
                    261,
                    260
                ]
            },
            "test": {
                "precision": [
                    0.970473005255614,
                    0.18295218295218296,
                    0.13513513513513514
                ],
                "recall": [
                    0.923524597617532,
                    0.3776824034334764,
                    0.29914529914529914
                ],
                "f1_score": [
                    0.946416922933557,
                    0.24649859943977587,
                    0.18617021276595747
                ],
                "support": [
                    10997,
                    233,
                    234
                ]
            }
        },
        "avg_macro": {
            "train": {
                "precision": 0.9720441199500088,
                "recall": 0.9719059721130797,
                "f1_score": 0.9717639932999749
            },
            "val": {
                "precision": 0.4233495722162397,
                "recall": 0.5557533763313967,
                "f1_score": 0.4559018482145872
            },
            "test": {
                "precision": 0.4295201077809773,
                "recall": 0.5334507667321026,
                "f1_score": 0.45969524504643006
            }
        },
        "annualised_returns": -0.07161901141267457
    },
    "CNNGRU-BNB-ITER19": {
        "per_class": {
            "train": {
                "precision": [
                    0.9671630016763633,
                    0.9571948998178507,
                    0.960032849712565
                ],
                "recall": [
                    0.9152668906308324,
                    0.9847278178581467,
                    0.9840987746702834
                ],
                "f1_score": [
                    0.9404995924629621,
                    0.9707661755876784,
                    0.9719168591224018
                ],
                "support": [
                    10716,
                    10673,
                    10691
                ]
            },
            "val": {
                "precision": [
                    0.9740549828178694,
                    0.15201005025125627,
                    0.1335149863760218
                ],
                "recall": [
                    0.8963554431180331,
                    0.46360153256704983,
                    0.3769230769230769
                ],
                "f1_score": [
                    0.9335913376425542,
                    0.22894985808893092,
                    0.1971830985915493
                ],
                "support": [
                    12649,
                    261,
                    260
                ]
            },
            "test": {
                "precision": [
                    0.9722059111372089,
                    0.16808149405772496,
                    0.13249211356466878
                ],
                "recall": [
                    0.9052305449243667,
                    0.4248927038626609,
                    0.358974358974359
                ],
                "f1_score": [
                    0.9375235938089846,
                    0.24087591240875914,
                    0.19354838709677422
                ],
                "support": [
                    10974,
                    233,
                    234
                ]
            }
        },
        "avg_macro": {
            "train": {
                "precision": 0.961463583735593,
                "recall": 0.9613644943864208,
                "f1_score": 0.9610608757243475
            },
            "val": {
                "precision": 0.4198600064817159,
                "recall": 0.5789600175360533,
                "f1_score": 0.4532414314410114
            },
            "test": {
                "precision": 0.42425983958653424,
                "recall": 0.5630325359204622,
                "f1_score": 0.45731596443817263
            }
        },
        "annualised_returns": 0.3324693147885813
    },
    "CNNGRU-BNB-ITER20": {
        "per_class": {
            "train": {
                "precision": [
                    0.9657381345239251,
                    0.9616769784837012,
                    0.9623553003372528
                ],
                "recall": [
                    0.9231768417146038,
                    0.983659204684991,
                    0.9832371018811696
                ],
                "f1_score": [
                    0.9439779896589346,
                    0.9725438924168845,
                    0.9726841402183426
                ],
                "support": [
                    10778,
                    10587,
                    10738
                ]
            },
            "val": {
                "precision": [
                    0.9713767219335148,
                    0.1956521739130435,
                    0.13535353535353536
                ],
                "recall": [
                    0.931056293485136,
                    0.41379310344827586,
                    0.2567049808429119
                ],
                "f1_score": [
                    0.9507892293407615,
                    0.2656826568265683,
                    0.17724867724867724
                ],
                "support": [
                    12648,
                    261,
                    261
                ]
            },
            "test": {
                "precision": [
                    0.9677085294671437,
                    0.17661691542288557,
                    0.12944162436548223
                ],
                "recall": [
                    0.9384643476673058,
                    0.30603448275862066,
                    0.21888412017167383
                ],
                "f1_score": [
                    0.9528621089223639,
                    0.22397476340694003,
                    0.1626794258373206
                ],
                "support": [
                    10953,
                    232,
                    233
                ]
            }
        },
        "avg_macro": {
            "train": {
                "precision": 0.9632568044482931,
                "recall": 0.9633577160935882,
                "f1_score": 0.963068674098054
            },
            "val": {
                "precision": 0.43412747706669785,
                "recall": 0.5338514592587745,
                "f1_score": 0.464573521138669
            },
            "test": {
                "precision": 0.4245890230851705,
                "recall": 0.4877943168658667,
                "f1_score": 0.44650543272220816
            }
        },
        "annualised_returns": 0.13126997420532538
    },
    "CNNGRU-BNB-ITER21": {
        "per_class": {
            "train": {
                "precision": [
                    0.951190710490061,
                    0.9476255088195387,
                    0.9494912457603814
                ],
                "recall": [
                    0.8953316042978882,
                    0.9769654014734682,
                    0.9765249363627793
                ],
                "f1_score": [
                    0.9224162610936159,
                    0.9620718155937183,
                    0.9628183677263431
                ],
                "support": [
                    10796,
                    10723,
                    10607
                ]
            },
            "val": {
                "precision": [
                    0.9732081911262799,
                    0.16174183514774496,
                    0.13135068153655513
                ],
                "recall": [
                    0.901945279139649,
                    0.3969465648854962,
                    0.40458015267175573
                ],
                "f1_score": [
                    0.936222605269638,
                    0.22983425414364642,
                    0.1983161833489242
                ],
                "support": [
                    12646,
                    262,
                    262
                ]
            },
            "test": {
                "precision": [
                    0.9712806486275276,
                    0.17598343685300208,
                    0.12444444444444444
                ],
                "recall": [
                    0.909531650201244,
                    0.36796536796536794,
                    0.3620689655172414
                ],
                "f1_score": [
                    0.9393925079125136,
                    0.2380952380952381,
                    0.185226019845645
                ],
                "support": [
                    10932,
                    231,
                    232
                ]
            }
        },
        "avg_macro": {
            "train": {
                "precision": 0.9494358216899936,
                "recall": 0.9496073140447119,
                "f1_score": 0.9491021481378924
            },
            "val": {
                "precision": 0.42210023593685997,
                "recall": 0.567823998898967,
                "f1_score": 0.4547910142540695
            },
            "test": {
                "precision": 0.4239028433083247,
                "recall": 0.5465219945612845,
                "f1_score": 0.4542379219511323
            }
        },
        "annualised_returns": 0.2821986371703762
    },
    "CNNGRU-BNB-ITER22": {
        "per_class": {
            "train": {
                "precision": [
                    0.9837233940094385,
                    0.9765992049150705,
                    0.9777528510001869
                ],
                "recall": [
                    0.9535991037251423,
                    0.9919243828576673,
                    0.9923157195711981
                ],
                "f1_score": [
                    0.9684270408647009,
                    0.9842021397678125,
                    0.984980460473657
                ],
                "support": [
                    10711,
                    10897,
                    10541
                ]
            },
            "val": {
                "precision": [
                    0.970568783068783,
                    0.162754303599374,
                    0.15172413793103448
                ],
                "recall": [
                    0.9285036380892123,
                    0.39543726235741444,
                    0.2509505703422053
                ],
                "f1_score": [
                    0.9490703314470492,
                    0.23059866962305986,
                    0.18911174785100285
                ],
                "support": [
                    12644,
                    263,
                    263
                ]
            },
            "test": {
                "precision": [
                    0.9691024547436262,
                    0.16630669546436286,
                    0.16201117318435754
                ],
                "recall": [
                    0.9371276693245348,
                    0.3347826086956522,
                    0.2510822510822511
                ],
                "f1_score": [
                    0.9528468921815302,
                    0.2222222222222222,
                    0.1969439728353141
                ],
                "support": [
                    10911,
                    230,
                    231
                ]
            }
        },
        "avg_macro": {
            "train": {
                "precision": 0.979358483308232,
                "recall": 0.9792797353846693,
                "f1_score": 0.9792032137020567
            },
            "val": {
                "precision": 0.4283490748663972,
                "recall": 0.5249638235962774,
                "f1_score": 0.45626024964037065
            },
            "test": {
                "precision": 0.4324734411307822,
                "recall": 0.5076641763674793,
                "f1_score": 0.4573376957463555
            }
        },
        "annualised_returns": 0.09096487437500134
    },
    "CNNGRU-BNB-ITER23": {
        "per_class": {
            "train": {
                "precision": [
                    0.9668586440335455,
                    0.95109233120561,
                    0.953461262553802
                ],
                "recall": [
                    0.9000188111361926,
                    0.9839099702380952,
                    0.985632183908046
                ],
                "f1_score": [
                    0.9322421939695067,
                    0.9672228571428572,
                    0.9692798541476755
                ],
                "support": [
                    10632,
                    10752,
                    10788
                ]
            },
            "val": {
                "precision": [
                    0.9746543778801844,
                    0.1606425702811245,
                    0.15177304964539007
                ],
                "recall": [
                    0.903131424956508,
                    0.4580152671755725,
                    0.4083969465648855
                ],
                "f1_score": [
                    0.93753078312264,
                    0.23785926660059464,
                    0.22130299896587388
                ],
                "support": [
                    12646,
                    262,
                    262
                ]
            },
            "test": {
                "precision": [
                    0.9703638497652582,
                    0.1474820143884892,
                    0.1335676625659051
                ],
                "recall": [
                    0.9111866274797943,
                    0.3565217391304348,
                    0.329004329004329
                ],
                "f1_score": [
                    0.9398446381205001,
                    0.20865139949109415,
                    0.19000000000000003
                ],
                "support": [
                    10888,
                    230,
                    231
                ]
            }
        },
        "avg_macro": {
            "train": {
                "precision": 0.9571374125976525,
                "recall": 0.956520321760778,
                "f1_score": 0.9562483017533464
            },
            "val": {
                "precision": 0.42902333260223297,
                "recall": 0.5898478795656553,
                "f1_score": 0.46556434956303616
            },
            "test": {
                "precision": 0.41713784223988415,
                "recall": 0.5322375652048527,
                "f1_score": 0.4461653458705314
            }
        },
        "annualised_returns": 0.05534586447713852
    },
    "CNNGRU-BNB-ITER24": {
        "per_class": {
            "train": {
                "precision": [
                    0.9796412990790111,
                    0.9674243121376644,
                    0.9694906020157995
                ],
                "recall": [
                    0.936081519221862,
                    0.9900178924569168,
                    0.9903533994991188
                ],
                "f1_score": [
                    0.9573661771672193,
                    0.9785907102299172,
                    0.9798109571441681
                ],
                "support": [
                    10795,
                    10619,
                    10781
                ]
            },
            "val": {
                "precision": [
                    0.9723316844135156,
                    0.17354196301564723,
                    0.13333333333333333
                ],
                "recall": [
                    0.9170488692076546,
                    0.46564885496183206,
                    0.2748091603053435
                ],
                "f1_score": [
                    0.9438814959508404,
                    0.2528497409326425,
                    0.17955112219451372
                ],
                "support": [
                    12646,
                    262,
                    262
                ]
            },
            "test": {
                "precision": [
                    0.9711787875876645,
                    0.18329938900203666,
                    0.1643192488262911
                ],
                "recall": [
                    0.9303331492729615,
                    0.391304347826087,
                    0.30434782608695654
                ],
                "f1_score": [
                    0.9503172737955347,
                    0.24965325936199723,
                    0.2134146341463415
                ],
                "support": [
                    10866,
                    230,
                    230
                ]
            }
        },
        "avg_macro": {
            "train": {
                "precision": 0.972185404410825,
                "recall": 0.9721509370592992,
                "f1_score": 0.9719226148471015
            },
            "val": {
                "precision": 0.4264023269208321,
                "recall": 0.5525022948249434,
                "f1_score": 0.45876078635933215
            },
            "test": {
                "precision": 0.4395991418053307,
                "recall": 0.5419951077286683,
                "f1_score": 0.4711283891012911
            }
        },
        "annualised_returns": 0.3449501905893655
    },
    "CNNGRU-BNB-ITER25": {
        "per_class": {
            "train": {
                "precision": [
                    0.9788499025341131,
                    0.9705161934137712,
                    0.9695473251028807
                ],
                "recall": [
                    0.9385104195869545,
                    0.9906472821557551,
                    0.9891770852771039
                ],
                "f1_score": [
                    0.9582558084060875,
                    0.9804784162771514,
                    0.9792638433473422
                ],
                "support": [
                    10701,
                    10799,
                    10718
                ]
            },
            "val": {
                "precision": [
                    0.9715058763845439,
                    0.15574963609898107,
                    0.12347560975609756
                ],
                "recall": [
                    0.9086595492289442,
                    0.4083969465648855,
                    0.30798479087452474
                ],
                "f1_score": [
                    0.9390323635174894,
                    0.2255005268703899,
                    0.17627856365614797
                ],
                "support": [
                    12645,
                    262,
                    263
                ]
            },
            "test": {
                "precision": [
                    0.970381917381138,
                    0.16984732824427481,
                    0.1262135922330097
                ],
                "recall": [
                    0.9183955739972337,
                    0.388646288209607,
                    0.2838427947598253
                ],
                "f1_score": [
                    0.943673314699891,
                    0.23638778220451528,
                    0.17473118279569894
                ],
                "support": [
                    10845,
                    229,
                    229
                ]
            }
        },
        "avg_macro": {
            "train": {
                "precision": 0.9729711403502549,
                "recall": 0.9727782623399378,
                "f1_score": 0.9726660226768603
            },
            "val": {
                "precision": 0.41691037407987414,
                "recall": 0.5416804288894516,
                "f1_score": 0.4469371513480091
            },
            "test": {
                "precision": 0.42214761261947414,
                "recall": 0.5302948856555553,
                "f1_score": 0.45159742656670177
            }
        },
        "annualised_returns": 0.13028585837960627
    },
    "CNNGRU-BNB-ITER26": {
        "per_class": {
            "train": {
                "precision": [
                    0.9831071462465597,
                    0.9771807140228193,
                    0.9756367663344407
                ],
                "recall": [
                    0.9529898804047838,
                    0.9922451649070354,
                    0.9910011248593926
                ],
                "f1_score": [
                    0.9678142663614705,
                    0.9846553242779658,
                    0.9832589285714285
                ],
                "support": [
                    10870,
                    10703,
                    10668
                ]
            },
            "val": {
                "precision": [
                    0.971681563779133,
                    0.16400580551523947,
                    0.1411764705882353
                ],
                "recall": [
                    0.9198165427803258,
                    0.4312977099236641,
                    0.2748091603053435
                ],
                "f1_score": [
                    0.945037981882439,
                    0.23764458464773924,
                    0.18652849740932645
                ],
                "support": [
                    12646,
                    262,
                    262
                ]
            },
            "test": {
                "precision": [
                    0.9707359474599189,
                    0.17992424242424243,
                    0.1507537688442211
                ],
                "recall": [
                    0.9287562372944003,
                    0.4148471615720524,
                    0.26200873362445415
                ],
                "f1_score": [
                    0.9492822062712505,
                    0.250990752972259,
                    0.1913875598086124
                ],
                "support": [
                    10822,
                    229,
                    229
                ]
            }
        },
        "avg_macro": {
            "train": {
                "precision": 0.9786415422012732,
                "recall": 0.9787453900570706,
                "f1_score": 0.9785761730702882
            },
            "val": {
                "precision": 0.4256212799608692,
                "recall": 0.5419744710031111,
                "f1_score": 0.45640368797983494
            },
            "test": {
                "precision": 0.4338046529094608,
                "recall": 0.5352040441636355,
                "f1_score": 0.4638868396840406
            }
        },
        "annualised_returns": 0.09013500980441269
    },
    "CNNGRU-BNB-ITER27": {
        "per_class": {
            "train": {
                "precision": [
                    0.9068370467453036,
                    0.8946133796698523,
                    0.8879117089153302
                ],
                "recall": [
                    0.767659023668639,
                    0.9635972300205877,
                    0.9568853372979
                ],
                "f1_score": [
                    0.8314640496695374,
                    0.9278248333032979,
                    0.9211091234347047
                ],
                "support": [
                    10816,
                    10686,
                    10762
                ]
            },
            "val": {
                "precision": [
                    0.9872506683117417,
                    0.12144420131291028,
                    0.10952970297029703
                ],
                "recall": [
                    0.7592314382857595,
                    0.8473282442748091,
                    0.6781609195402298
                ],
                "f1_score": [
                    0.85835605417244,
                    0.21244019138755982,
                    0.18859882791688865
                ],
                "support": [
                    12647,
                    262,
                    261
                ]
            },
            "test": {
                "precision": [
                    0.9860279441117764,
                    0.13022618231665525,
                    0.11553473848555816
                ],
                "recall": [
                    0.7775925925925926,
                    0.8333333333333334,
                    0.6462882096069869
                ],
                "f1_score": [
                    0.8694931925247192,
                    0.22525192649673978,
                    0.1960264900662252
                ],
                "support": [
                    10800,
                    228,
                    229
                ]
            }
        },
        "avg_macro": {
            "train": {
                "precision": 0.8964540451101621,
                "recall": 0.8960471969957089,
                "f1_score": 0.8934660021358467
            },
            "val": {
                "precision": 0.4060748575316497,
                "recall": 0.7615735340335995,
                "f1_score": 0.41979835782562946
            },
            "test": {
                "precision": 0.4105962883046632,
                "recall": 0.7524047118443044,
                "f1_score": 0.43025720302922804
            }
        },
        "annualised_returns": 0.21049569908359267
    },
    "CNNGRU-BNB-ITER28": {
        "per_class": {
            "train": {
                "precision": [
                    0.9768385628031278,
                    0.9674087266251113,
                    0.9677743290122329
                ],
                "recall": [
                    0.9320929353985644,
                    0.9903372835004558,
                    0.988069717587846
                ],
                "f1_score": [
                    0.9539413271470687,
                    0.9787387387387387,
                    0.9778167227782133
                ],
                "support": [
                    10588,
                    10970,
                    10729
                ]
            },
            "val": {
                "precision": [
                    0.9712497886013868,
                    0.14842578710644677,
                    0.1255539143279173
                ],
                "recall": [
                    0.9082713901628974,
                    0.37786259541984735,
                    0.3244274809160305
                ],
                "f1_score": [
                    0.9387054593004248,
                    0.21313240043057052,
                    0.1810436634717785
                ],
                "support": [
                    12646,
                    262,
                    262
                ]
            },
            "test": {
                "precision": [
                    0.9706314243759178,
                    0.17034068136272545,
                    0.1346153846153846
                ],
                "recall": [
                    0.9198441413860284,
                    0.3744493392070485,
                    0.30701754385964913
                ],
                "f1_score": [
                    0.9445555873106602,
                    0.23415977961432505,
                    0.18716577540106952
                ],
                "support": [
                    10779,
                    227,
                    228
                ]
            }
        },
        "avg_macro": {
            "train": {
                "precision": 0.9706738728134906,
                "recall": 0.970166645495622,
                "f1_score": 0.9701655962213401
            },
            "val": {
                "precision": 0.4150764966785836,
                "recall": 0.5368538221662584,
                "f1_score": 0.44429384106759123
            },
            "test": {
                "precision": 0.42519583011800927,
                "recall": 0.5337703414842421,
                "f1_score": 0.45529371410868497
            }
        },
        "annualised_returns": 0.10885397468380997
    },
    "CNNGRU-BNB-ITER29": {
        "per_class": {
            "train": {
                "precision": [
                    0.8950571154051458,
                    0.8987452073893343,
                    0.8966599808145113
                ],
                "recall": [
                    0.7812878576087969,
                    0.9525304765422977,
                    0.9563761510557157
                ],
                "f1_score": [
                    0.8343118718280427,
                    0.9248565279770444,
                    0.9255558556125664
                ],
                "support": [
                    10731,
                    10828,
                    10751
                ]
            },
            "val": {
                "precision": [
                    0.9742998633879781,
                    0.18264248704663213,
                    0.119533527696793
                ],
                "recall": [
                    0.9023406610786019,
                    0.5381679389312977,
                    0.31297709923664124
                ],
                "f1_score": [
                    0.9369406355201576,
                    0.27272727272727276,
                    0.1729957805907173
                ],
                "support": [
                    12646,
                    262,
                    262
                ]
            },
            "test": {
                "precision": [
                    0.9721202500248041,
                    0.18803418803418803,
                    0.1170018281535649
                ],
                "recall": [
                    0.9109334325027891,
                    0.4845814977973568,
                    0.2807017543859649
                ],
                "f1_score": [
                    0.9405327573794097,
                    0.270935960591133,
                    0.16516129032258062
                ],
                "support": [
                    10756,
                    227,
                    228
                ]
            }
        },
        "avg_macro": {
            "train": {
                "precision": 0.8968207678696638,
                "recall": 0.8967314950689368,
                "f1_score": 0.8949080851392178
            },
            "val": {
                "precision": 0.42549195937713447,
                "recall": 0.5844952330821802,
                "f1_score": 0.4608878962793826
            },
            "test": {
                "precision": 0.4257187554041857,
                "recall": 0.5587388948953703,
                "f1_score": 0.45887666943104105
            }
        },
        "annualised_returns": 0.5825843900479204
    }
}